{
  "petCardForm": {
    "en": {
      "name": "Name",
      "images": "Images",
      "address": "Address",
      "itn": "ITN",
      "type": "Type",
      "status": "Status",
      "age": "Age",
      "create": "Create",
      "loading": "Loading",
      "description": "Description",
      "fillInTheField": "Fill in the field",
      "characteristics": "Characteristics",
      "bodyType": "Body Type",
      "thin": "Thin",
      "average": "Average",
      "full": "Full",
      "weight": "Weight",
      "ageSmall": "Small (0-1 years)",
      "ageYoung": "Young (1-7 years)",
      "ageAdult": "Adult (7-12 years)",
      "ageOld": "Old (12+ years)",
      "ageUnknown": "Unknown",
      "breed": "Breed",
      "search": "Search",
      "enterBreed": "Enter breed",
      "bengal": "Bengal",
      "european": "European",
      "beagle": "Beagle",
      "enterValue": "Enter value",
      "allergenicity": "Allergenicity",
      "woolType": "Wool type",
      "hairless": "Hairless",
      "fluffy": "Fluffy",
      "tough": "Tough",
      "long": "Long",
      "short": "Short",
      "sterilization": "Sterilization",
      "healthIssues": "Health Issues",
      "uploadFile": "Upload File",
      "vaccinations": "Vaccinations",
      "reportLostPet": "Report Lost Pet",
      "reportDescription": "Lost a pet or found a pet from an announcement? Report it.",
      "announcementType": "Announcement Type",
      "shelterFormat": "Shelter Format",
      "shelterDescription": "Shelter format announcements help find families for animals and attract financial support.",
      "userFormat": "User Format",
      "userDescription": "User format announcements attract more attention and help quickly find a home for the pet.",
      "submit": "Submit",
      "next": "Next",
      "upload": "Upload",
      "edit": "Edit",
      "namePet": "Pet Name",
      "gender": "Gender",
      "male": "Male",
      "female": "Female",
      "category": "Category",
      "cats": "Cats",
      "dogs": "Dogs",
      "selectCategory": "Select Category",
      "petName": "Pet Name",
      "enterPetName": "Enter pet name",
      "mainInfo": "Main Information",
      "descriptionFormTitle": "Ad Description",
      "enterDescription": "Enter description",
      "addPhotos": "Add Photos",
      "maxImages": "No more than 10 images",
      "save": "Save and exit"
    },
    "ru": {
      "name": "Имя",
      "images": "Изображения",
      "address": "Адрес",
      "itn": "ИНН",
      "type": "Тип",
      "status": "Статус",
      "age": "Возраст",
      "create": "Создать",
      "loading": "Загрузка",
      "description": "Описание",
      "fillInTheField": "Заполните поле",
      "characteristics": "Характеристики",
      "bodyType": "Телосложение",
      "thin": "Худое",
      "average": "Среднее",
      "full": "Полное",
      "weight": "Вес",
      "ageSmall": "Маленький (0-1 год)",
      "ageYoung": "Молодой (1-7 лет)",
      "ageAdult": "Взрослый (7-12 лет)",
      "ageOld": "Старый (12+ лет)",
      "ageUnknown": "Неизвестно",
      "breed": "Порода",
      "search": "Поиск",
      "enterBreed": "Введите породу",
      "bengal": "Бенгальская",
      "european": "Европейская",
      "beagle": "Бигль",
      "enterValue": "Введите значение",
      "allergenicity": "Аллергенность",
      "woolType": "Тип шерсти",
      "hairless": "Бесшерстная",
      "fluffy": "Пушистая",
      "tough": "Жесткая",
      "long": "Длинная",
      "short": "Короткая",
      "sterilization": "Стерилизация",
      "healthIssues": "Наличие болезней",
      "uploadFile": "Загрузить файл",
      "vaccinations": "Прививки",
      "reportLostPet": "Сообщить о потере питомца",
      "reportDescription": "Потеряли домашнего питомца или нашли питомца из объявления? Сообщите об этом.",
      "announcementType": "Вид объявления",
      "shelterFormat": "Формат приюта",
      "shelterDescription": "Объявления формата приют помогает находить семьи для животных и привлекает материальную помощь.",
      "userFormat": "Формат пользователя",
      "userDescription": "Объявление от лица пользователя привлекает больше внимания и помогает быстро найти дом для питомца.",
      "submit": "Отправить",
      "next": "Далее",
      "upload": "Загрузить",
      "edit": "Редактировать",
      "namePet": "Имя питомца",
      "gender": "Пол",
      "male": "Мужской",
      "female": "Женский",
      "category": "Категория",
      "cats": "Кошки",
      "dogs": "Собаки",
      "selectCategory": "Выберите категорию",
      "petName": "Имя питомца",
      "enterPetName": "Введите имя питомца",
      "mainInfo": "Главная информация",
      "descriptionFormTitle": "Описание объявления",
      "enterDescription": "Введите описание",
      "addPhotos": "Добавьте фотографии",
      "maxImages": "Не более 10 изображений",
      "save": "Сохранить и выйти"
    }
  }
}
